setup.py
cess/__init__.py
cess/cli.py
cess/sim.py
cess/util.py
cess.egg-info/PKG-INFO
cess.egg-info/SOURCES.txt
cess.egg-info/dependency_links.txt
cess.egg-info/entry_points.txt
cess.egg-info/requires.txt
cess.egg-info/top_level.txt
cess/agent/__init__.py
cess/agent/action.py
cess/agent/outcome.py
cess/agent/prereq.py
cess/agent/search.py
cess/agent/state.py
cess/agent/utility.py
cess/cluster/__init__.py
cess/cluster/arbiter.py
cess/cluster/client.py
cess/cluster/protocol.py
cess/cluster/server.py
cess/cluster/worker.py