Metadata-Version: 1.0
Name: cess
Version: 0.0.1
Summary: a distributed agent-based modeling framework
Home-page: https://github.com/frnsys/cess
Author: Francis Tseng (@frnsys)
Author-email: f@frnsys.com
License: MIT
Platform: UNKNOWN
